pyblueprint/__init__.py
pyblueprint/blueprint.py
pyblueprint/colors.py
pyblueprint/static.py
pyblueprint-0.0.4.dist-info/LICENSE
pyblueprint-0.0.4.dist-info/METADATA
pyblueprint-0.0.4.dist-info/WHEEL
pyblueprint-0.0.4.dist-info/top_level.txt
pyblueprint-0.0.4.dist-info/RECORD
